{
  "Guild": 414234792121597953,
  "Month": 3,
  "Day": 26,
  "Character": "Jurota Shishida",
  "Description": "Jurota's Quirk, Beast, allows him transform into a large, monstrous beast-man. This monster form drastically augments his strength, speed, and durability, as well as his senses of hearing and smell. While he is transformed, he becomes more wild, making him reckless.",
  "ColorNo": "#a06b58",
  "EngVAName": "Patric Carroll",
  "EngVALink": "https://www.behindthevoiceactors.com/Patric-Carroll/",
  "JPVAName": "Junichi Suwabe",
  "JPVALink": "https://www.behindthevoiceactors.com/Junichi-Suwabe/",
  "ThumbnailLink": "",
  "ImageLink": "https://i.imgur.com/YqBzek4.gif",
  "WikiLink": "https://myheroacademia.fandom.com/wiki/Jurota_Shishida#Quirk",
} 
