{
  "Guild": 414234792121597953,
  "Month": 10,
  "Day": 8,
  "Character": "Minoru Mineta",
  "Description": "Minoru's Quirk, Pop Off, allows him to produce and pluck ball-shaped objects from his head; the balls grow back just as fast as they're plucked. The balls are incredibly sticky and will stick to any surface; the sole exception being Minoru himself. The duration of their adhesive quality is determined by his overall health. If he plucks too many, it will cause him to start bleeding from his scalp.",
  "ColorNo": "#2f123e",
  "EngVAName": "Brina Palencia",
  "EngVALink": "https://www.behindthevoiceactors.com/Brina-Palencia/",
  "JPVAName": "Ryō Hirohashi",
  "JPVALink": "https://www.behindthevoiceactors.com/Ryo-Hirohashi/",
  "ThumbnailLink": "",
  "ImageLink": "https://i.imgur.com/7Aqn6Ym.gif",
  "WikiLink": "https://myheroacademia.fandom.com/wiki/Minoru_Mineta#Quirk",
} 
