{
  "Guild": 414234792121597953,
  "Month": 7,
  "Day": 4,
  "Character": "Star & Stripe",
  "Description": "Cathleen Bate's Quirk, New Order, allows her to set a rule onto her surroundings, which lets her manipulate and bestow new properties onto herself and the world around her. In order to activate her Quirk, she has to first make physical contact with the target and speak its name, then explain the rule she wishes to impose. She can only impose two rules at any given time.",
  "ColorNo": "#19296b",
  "EngVAName": "Natalie Van Sistine",
  "EngVALink": "https://www.behindthevoiceactors.com/Natalie-Van-Sistine/",
  "JPVAName": "Romi Park",
  "JPVALink": "https://www.behindthevoiceactors.com/Romi-Park/",
  "ThumbnailLink": "",
  "ImageLink": "https://i.imgur.com/b5avRov.gif",
  "WikiLink": "https://myheroacademia.fandom.com/wiki/Cathleen_Bate#Former_Quirk",
} 
